mastercard_moneysend-1.0.4.dist-info/DESCRIPTION.rst
mastercard_moneysend-1.0.4.dist-info/METADATA
mastercard_moneysend-1.0.4.dist-info/RECORD
mastercard_moneysend-1.0.4.dist-info/WHEEL
mastercard_moneysend-1.0.4.dist-info/metadata.json
mastercard_moneysend-1.0.4.dist-info/top_level.txt
mastercardmoneysend/__init__.py
mastercardmoneysend/cardeligibility.py
mastercardmoneysend/cardmapping.py
mastercardmoneysend/funding.py
mastercardmoneysend/payment.py
mastercardmoneysend/resourceconfig.py
mastercardmoneysend/sanctionscreening.py
mastercardmoneysend/transferreversal.py
